GeoAnalyze/__init__.py
GeoAnalyze/core.py
GeoAnalyze/file.py
GeoAnalyze/raster.py
GeoAnalyze/shape.py
GeoAnalyze/stream.py
GeoAnalyze/visual.py
GeoAnalyze/watershed.py
geoanalyze-1.2.5.dist-info/licenses/LICENSE.txt
geoanalyze-1.2.5.dist-info/METADATA
geoanalyze-1.2.5.dist-info/WHEEL
geoanalyze-1.2.5.dist-info/top_level.txt
geoanalyze-1.2.5.dist-info/RECORD
