Metadata-Version: 2.4
Name: GeoAnalyze
Version: 1.2.5
Summary: A Python package offering toolkits for geospatial processing, watershed delineation, and hydrologic analysis.
Author-email: Debasish Pal <bestdebasish@gmail.com>
License-Expression: MIT
Project-URL: Homepage, https://github.com/debpal/GeoAnalyze
Project-URL: Documentation, https://geoanalyze.readthedocs.io/en/latest/
Keywords: GIS,Watershed,Hydrology,Spatial analysis,Raster,Vector
Classifier: Development Status :: 5 - Production/Stable
Classifier: Programming Language :: Python :: 3.10
Classifier: Programming Language :: Python :: 3.11
Classifier: Programming Language :: Python :: 3.12
Classifier: Programming Language :: Python :: 3.13
Classifier: Operating System :: OS Independent
Classifier: Intended Audience :: Education
Classifier: Intended Audience :: Science/Research
Classifier: Topic :: Scientific/Engineering
Classifier: Topic :: Scientific/Engineering :: GIS
Classifier: Topic :: Scientific/Engineering :: Hydrology
Requires-Python: >=3.10
License-File: LICENSE.txt
Requires-Dist: geopandas
Requires-Dist: rasterio
Requires-Dist: fiona
Requires-Dist: pyflwdir
Requires-Dist: matplotlib
Dynamic: license-file
